{
  "__inputs": [],
  "__requires": [
    { "type": "grafana", "id": "grafana", "name": "Grafana", "version": "10.0.0" },
    { "type": "datasource", "id": "prometheus", "name": "Prometheus", "version": "1.0.0" },
    { "type": "datasource", "id": "loki", "name": "Loki", "version": "1.0.0" }
  ],
  "annotations": { "list": [] },
  "editable": true,
  "fiscalYearStartMonth": 0,
  "graphTooltip": 1,
  "id": null,
  "links": [],
  "liveNow": false,
  "panels": [

    {
      "collapsed": false,
      "gridPos": { "h": 1, "w": 24, "x": 0, "y": 0 },
      "id": 100,
      "title": "Golden Signals вЂ” Freshness & Lag",
      "type": "row"
    },

    {
      "datasource": { "type": "prometheus", "uid": "Prometheus" },
      "fieldConfig": {
        "defaults": {
          "color": { "mode": "thresholds" },
          "thresholds": {
            "mode": "absolute",
            "steps": [
              { "color": "green", "value": null },
              { "color": "yellow", "value": 600 },
              { "color": "red", "value": 1800 }
            ]
          },
          "unit": "s",
          "mappings": []
        },
        "overrides": []
      },
      "gridPos": { "h": 5, "w": 12, "x": 0, "y": 1 },
      "id": 1,
      "options": {
        "reduceOptions": { "calcs": ["lastNotNull"] },
        "orientation": "auto",
        "textMode": "auto",
        "colorMode": "background",
        "graphMode": "none"
      },
      "pluginVersion": "10.0.0",
      "targets": [
        {
          "datasource": { "type": "prometheus", "uid": "Prometheus" },
          "expr": "pklpo_pipeline_candle_lag_seconds",
          "legendFormat": "{{timeframe}}",
          "refId": "A"
        }
      ],
      "title": "Candle Freshness Lag by Timeframe",
      "type": "stat"
    },

    {
      "datasource": { "type": "prometheus", "uid": "Prometheus" },
      "fieldConfig": {
        "defaults": {
          "color": { "mode": "palette-classic" },
          "unit": "s",
          "custom": { "lineWidth": 2, "fillOpacity": 10 }
        },
        "overrides": []
      },
      "gridPos": { "h": 5, "w": 12, "x": 12, "y": 1 },
      "id": 2,
      "options": { "tooltip": { "mode": "multi" }, "legend": { "displayMode": "list" } },
      "targets": [
        {
          "datasource": { "type": "prometheus", "uid": "Prometheus" },
          "expr": "pklpo_pipeline_candle_lag_seconds",
          "legendFormat": "{{timeframe}}",
          "refId": "A"
        }
      ],
      "title": "Candle Lag History",
      "type": "timeseries"
    },

    {
      "collapsed": false,
      "gridPos": { "h": 1, "w": 24, "x": 0, "y": 6 },
      "id": 101,
      "title": "Pipeline Queue & Eligibility",
      "type": "row"
    },

    {
      "datasource": { "type": "prometheus", "uid": "Prometheus" },
      "fieldConfig": {
        "defaults": {
          "color": { "mode": "thresholds" },
          "thresholds": {
            "mode": "absolute",
            "steps": [
              { "color": "green", "value": null },
              { "color": "yellow", "value": 5 },
              { "color": "red", "value": 20 }
            ]
          },
          "unit": "short",
          "mappings": []
        },
        "overrides": []
      },
      "gridPos": { "h": 4, "w": 6, "x": 0, "y": 7 },
      "id": 3,
      "options": {
        "reduceOptions": { "calcs": ["lastNotNull"] },
        "orientation": "auto",
        "textMode": "value_and_name",
        "colorMode": "background",
        "graphMode": "none"
      },
      "pluginVersion": "10.0.0",
      "targets": [
        {
          "datasource": { "type": "prometheus", "uid": "Prometheus" },
          "expr": "pklpo_pipeline_recalc_queue_rows",
          "legendFormat": "{{status}}",
          "refId": "A"
        }
      ],
      "title": "Recalc Queue Depth by Status",
      "type": "stat"
    },

    {
      "datasource": { "type": "prometheus", "uid": "Prometheus" },
      "fieldConfig": {
        "defaults": {
          "color": { "mode": "palette-classic" },
          "unit": "short",
          "custom": { "lineWidth": 2, "fillOpacity": 10 }
        },
        "overrides": []
      },
      "gridPos": { "h": 4, "w": 10, "x": 6, "y": 7 },
      "id": 4,
      "targets": [
        {
          "datasource": { "type": "prometheus", "uid": "Prometheus" },
          "expr": "pklpo_pipeline_recalc_queue_rows",
          "legendFormat": "queue:{{status}}",
          "refId": "A"
        },
        {
          "datasource": { "type": "prometheus", "uid": "Prometheus" },
          "expr": "pklpo_pipeline_bootstrap_state_rows",
          "legendFormat": "bootstrap:{{status}}",
          "refId": "B"
        }
      ],
      "title": "Queue & Bootstrap History",
      "type": "timeseries"
    },

    {
      "datasource": { "type": "prometheus", "uid": "Prometheus" },
      "fieldConfig": {
        "defaults": { "unit": "short", "color": { "mode": "palette-classic" } },
        "overrides": []
      },
      "gridPos": { "h": 4, "w": 8, "x": 16, "y": 7 },
      "id": 5,
      "options": {
        "reduceOptions": { "calcs": ["lastNotNull"] },
        "displayLabels": ["name"],
        "pieType": "donut"
      },
      "targets": [
        {
          "datasource": { "type": "prometheus", "uid": "Prometheus" },
          "expr": "sum by (state) (pklpo_pipeline_eligibility_state_rows)",
          "legendFormat": "{{state}}",
          "refId": "A"
        }
      ],
      "title": "Eligibility State Distribution",
      "type": "piechart"
    },

    {
      "collapsed": false,
      "gridPos": { "h": 1, "w": 24, "x": 0, "y": 11 },
      "id": 102,
      "title": "Pipeline Alerts & Dependency Health",
      "type": "row"
    },

    {
      "datasource": { "type": "prometheus", "uid": "Prometheus" },
      "fieldConfig": {
        "defaults": {
          "color": { "mode": "thresholds" },
          "thresholds": {
            "mode": "absolute",
            "steps": [
              { "color": "green", "value": null },
              { "color": "yellow", "value": 1 },
              { "color": "red", "value": 5 }
            ]
          },
          "unit": "short",
          "mappings": [{ "options": { "0": { "text": "OK" } }, "type": "value" }]
        },
        "overrides": []
      },
      "gridPos": { "h": 4, "w": 6, "x": 0, "y": 12 },
      "id": 6,
      "options": {
        "reduceOptions": { "calcs": ["lastNotNull"] },
        "textMode": "value_and_name",
        "colorMode": "background",
        "graphMode": "none"
      },
      "pluginVersion": "10.0.0",
      "targets": [
        {
          "datasource": { "type": "prometheus", "uid": "Prometheus" },
          "expr": "pklpo_pipeline_alerts",
          "legendFormat": "{{severity}}",
          "refId": "A"
        }
      ],
      "title": "Pipeline Alerts by Severity",
      "type": "stat"
    },

    {
      "datasource": { "type": "prometheus", "uid": "Prometheus" },
      "fieldConfig": {
        "defaults": {
          "color": { "mode": "thresholds" },
          "thresholds": {
            "mode": "absolute",
            "steps": [
              { "color": "red", "value": null },
              { "color": "green", "value": 1 }
            ]
          },
          "unit": "short",
          "mappings": [
            { "options": { "0": { "text": "DOWN", "color": "red" }, "1": { "text": "UP", "color": "green" } }, "type": "value" }
          ]
        },
        "overrides": []
      },
      "gridPos": { "h": 4, "w": 6, "x": 6, "y": 12 },
      "id": 7,
      "options": {
        "reduceOptions": { "calcs": ["lastNotNull"] },
        "textMode": "value_and_name",
        "colorMode": "background",
        "graphMode": "none"
      },
      "pluginVersion": "10.0.0",
      "targets": [
        {
          "datasource": { "type": "prometheus", "uid": "Prometheus" },
          "expr": "pklpo_dependency_postgres_up",
          "legendFormat": "Postgres",
          "refId": "A"
        },
        {
          "datasource": { "type": "prometheus", "uid": "Prometheus" },
          "expr": "pklpo_dependency_okx_up",
          "legendFormat": "OKX API",
          "refId": "B"
        }
      ],
      "title": "Dependency Health",
      "type": "stat"
    },

    {
      "datasource": { "type": "prometheus", "uid": "Prometheus" },
      "fieldConfig": {
        "defaults": {
          "color": { "mode": "palette-classic" },
          "unit": "short",
          "custom": { "lineWidth": 2, "fillOpacity": 10 }
        },
        "overrides": []
      },
      "gridPos": { "h": 4, "w": 12, "x": 12, "y": 12 },
      "id": 8,
      "targets": [
        {
          "datasource": { "type": "prometheus", "uid": "Prometheus" },
          "expr": "pklpo_pipeline_alerts",
          "legendFormat": "{{severity}}",
          "refId": "A"
        },
        {
          "datasource": { "type": "prometheus", "uid": "Prometheus" },
          "expr": "pklpo_dependency_postgres_up",
          "legendFormat": "postgres_up",
          "refId": "B"
        },
        {
          "datasource": { "type": "prometheus", "uid": "Prometheus" },
          "expr": "pklpo_dependency_okx_up",
          "legendFormat": "okx_up",
          "refId": "C"
        }
      ],
      "title": "Alerts & Dependency Health History",
      "type": "timeseries"
    },

    {
      "collapsed": false,
      "gridPos": { "h": 1, "w": 24, "x": 0, "y": 16 },
      "id": 103,
      "title": "Repair Outcomes",
      "type": "row"
    },

    {
      "datasource": { "type": "prometheus", "uid": "Prometheus" },
      "fieldConfig": {
        "defaults": {
          "color": { "mode": "palette-classic" },
          "unit": "short",
          "custom": { "lineWidth": 2, "fillOpacity": 10 }
        },
        "overrides": []
      },
      "gridPos": { "h": 5, "w": 12, "x": 0, "y": 17 },
      "id": 9,
      "targets": [
        {
          "datasource": { "type": "prometheus", "uid": "Prometheus" },
          "expr": "sum by (timeframe, mode) (pklpo_swap_repair_rows_written)",
          "legendFormat": "written {{timeframe}} {{mode}}",
          "refId": "A"
        },
        {
          "datasource": { "type": "prometheus", "uid": "Prometheus" },
          "expr": "sum by (timeframe, mode) (pklpo_swap_repair_remaining_gap_tasks)",
          "legendFormat": "remaining_gaps {{timeframe}} {{mode}}",
          "refId": "B"
        }
      ],
      "title": "Repair: Rows Written & Remaining Gaps",
      "type": "timeseries"
    },

    {
      "datasource": { "type": "prometheus", "uid": "Prometheus" },
      "fieldConfig": {
        "defaults": {
          "color": { "mode": "palette-classic" },
          "unit": "short",
          "custom": { "lineWidth": 2, "fillOpacity": 10 }
        },
        "overrides": []
      },
      "gridPos": { "h": 5, "w": 12, "x": 12, "y": 17 },
      "id": 10,
      "targets": [
        {
          "datasource": { "type": "prometheus", "uid": "Prometheus" },
          "expr": "pklpo_swap_sync_rows_upserted",
          "legendFormat": "upserted {{mode}}",
          "refId": "A"
        },
        {
          "datasource": { "type": "prometheus", "uid": "Prometheus" },
          "expr": "pklpo_swap_sync_symbols_processed",
          "legendFormat": "symbols {{mode}}",
          "refId": "B"
        },
        {
          "datasource": { "type": "prometheus", "uid": "Prometheus" },
          "expr": "pklpo_swap_sync_errors",
          "legendFormat": "errors {{mode}}",
          "refId": "C"
        }
      ],
      "title": "Swap Sync: Throughput & Errors",
      "type": "timeseries"
    },

    {
      "collapsed": false,
      "gridPos": { "h": 1, "w": 24, "x": 0, "y": 22 },
      "id": 104,
      "title": "Logs вЂ” Loki Correlation",
      "type": "row"
    },

    {
      "datasource": { "type": "loki", "uid": "Loki" },
      "gridPos": { "h": 8, "w": 24, "x": 0, "y": 23 },
      "id": 11,
      "options": {
        "dedupStrategy": "none",
        "enableLogDetails": true,
        "prettifyLogMessage": false,
        "showCommonLabels": false,
        "showLabels": false,
        "showTime": true,
        "sortOrder": "Descending",
        "wrapLogMessage": false
      },
      "targets": [
        {
          "datasource": { "type": "loki", "uid": "Loki" },
          "expr": "{job=~\"pklpo_app|pklpo_airflow\"} | json | component=~\".+\"",
          "legendFormat": "",
          "refId": "A"
        }
      ],
      "title": "Pipeline Logs (filter by run_id in Explore в†’ {job=~\"pklpo_app|pklpo_airflow\"} | json | run_id=\"<RUN_ID>\")",
      "type": "logs",
      "description": "Use run_id as the primary Loki lookup. Log lines with non-empty trace_id expose a Grafana derived link to Tempo."
    },

    {
      "datasource": { "type": "loki", "uid": "Loki" },
      "gridPos": { "h": 5, "w": 12, "x": 0, "y": 31 },
      "id": 12,
      "options": {
        "dedupStrategy": "none",
        "enableLogDetails": true,
        "prettifyLogMessage": false,
        "showCommonLabels": false,
        "showLabels": false,
        "showTime": true,
        "sortOrder": "Descending",
        "wrapLogMessage": false
      },
      "targets": [
        {
          "datasource": { "type": "loki", "uid": "Loki" },
          "expr": "{job=~\"pklpo_app|pklpo_airflow\"} | json | error_type != \"-\" | error_type != \"\"",
          "legendFormat": "",
          "refId": "A"
        },
        {
          "datasource": { "type": "loki", "uid": "Loki" },
          "expr": "{job=~\"pklpo_app|pklpo_airflow\"} | json | level = \"ERROR\"",
          "legendFormat": "",
          "refId": "B"
        }
      ],
      "title": "Error Events (error_type != \"-\" or level=ERROR)",
      "type": "logs"
    },

    {
      "datasource": { "type": "loki", "uid": "Loki" },
      "gridPos": { "h": 5, "w": 12, "x": 12, "y": 31 },
      "id": 13,
      "options": {
        "dedupStrategy": "none",
        "enableLogDetails": true,
        "prettifyLogMessage": false,
        "showCommonLabels": false,
        "showLabels": false,
        "showTime": true,
        "sortOrder": "Descending",
        "wrapLogMessage": false
      },
      "targets": [
        {
          "datasource": { "type": "loki", "uid": "Loki" },
          "expr": "{job=~\"pklpo_app|pklpo_airflow\"} | json | line_format \"{{.message}}\" |~ \"lock_conflict|lock conflict|LockConflict\"",
          "legendFormat": "",
          "refId": "A"
        }
      ],
      "title": "Lock Conflicts (from Loki)",
      "type": "logs"
    },

    {
      "collapsed": false,
      "gridPos": { "h": 1, "w": 24, "x": 0, "y": 37 },
      "id": 200,
      "title": "RED вЂ” Rate / Errors / Duration",
      "type": "row"
    },

    {
      "datasource": { "type": "prometheus", "uid": "Prometheus" },
      "fieldConfig": {
        "defaults": { "unit": "short", "custom": { "lineWidth": 2 } },
        "overrides": []
      },
      "gridPos": { "h": 6, "w": 8, "x": 0, "y": 38 },
      "id": 201,
      "options": { "tooltip": { "mode": "multi" }, "legend": { "displayMode": "list" } },
      "targets": [
        {
          "datasource": { "type": "prometheus", "uid": "Prometheus" },
          "expr": "pklpo_swap_sync_rows_upserted",
          "legendFormat": "swap_sync rows (per run)",
          "refId": "A"
        },
        {
          "datasource": { "type": "prometheus", "uid": "Prometheus" },
          "expr": "pklpo_swap_sync_symbols_processed",
          "legendFormat": "swap_sync symbols (per run)",
          "refId": "B"
        }
      ],
      "title": "RED вЂ” Throughput (per-run counts, swap_sync only)",
      "type": "timeseries"
    },

    {
      "datasource": { "type": "prometheus", "uid": "Prometheus" },
      "fieldConfig": {
        "defaults": { "unit": "short", "color": { "mode": "fixed", "fixedColor": "red" }, "custom": { "lineWidth": 2 } },
        "overrides": []
      },
      "gridPos": { "h": 6, "w": 8, "x": 8, "y": 38 },
      "id": 202,
      "options": { "tooltip": { "mode": "multi" }, "legend": { "displayMode": "list" } },
      "targets": [
        {
          "datasource": { "type": "prometheus", "uid": "Prometheus" },
          "expr": "pklpo_swap_sync_errors",
          "legendFormat": "swap_sync errors (per run)",
          "refId": "A"
        }
      ],
      "title": "RED вЂ” Error Count (per-run, swap_sync only)",
      "type": "timeseries"
    },

    {
      "datasource": { "type": "prometheus", "uid": "Prometheus" },
      "fieldConfig": {
        "defaults": { "unit": "s", "custom": { "lineWidth": 2 } },
        "overrides": []
      },
      "gridPos": { "h": 6, "w": 8, "x": 16, "y": 38 },
      "id": 203,
      "options": { "tooltip": { "mode": "multi" }, "legend": { "displayMode": "list" } },
      "targets": [
        {
          "datasource": { "type": "prometheus", "uid": "Prometheus" },
          "expr": "histogram_quantile(0.95, rate(pklpo_swap_sync_db_write_latency_seconds_bucket[5m]))",
          "legendFormat": "DB write p95 est. (swap_sync)",
          "refId": "A"
        },
        {
          "datasource": { "type": "prometheus", "uid": "Prometheus" },
          "expr": "histogram_quantile(0.50, rate(pklpo_swap_sync_db_write_latency_seconds_bucket[5m]))",
          "legendFormat": "DB write p50 est. (swap_sync)",
          "refId": "B"
        }
      ],
      "title": "RED вЂ” DB Write Latency (est. p50/p95 вЂ” representative, not true distribution)",
      "type": "timeseries"
    },

    {
      "collapsed": false,
      "gridPos": { "h": 1, "w": 24, "x": 0, "y": 45 },
      "id": 300,
      "title": "USE вЂ” Utilisation / Saturation / Errors",
      "type": "row"
    },

    {
      "datasource": { "type": "prometheus", "uid": "Prometheus" },
      "fieldConfig": {
        "defaults": {
          "color": { "mode": "thresholds" },
          "thresholds": {
            "mode": "absolute",
            "steps": [
              { "color": "green", "value": null },
              { "color": "yellow", "value": 0.7 },
              { "color": "red", "value": 0.9 }
            ]
          },
          "unit": "percentunit",
          "min": 0,
          "max": 1,
          "mappings": []
        },
        "overrides": []
      },
      "gridPos": { "h": 5, "w": 6, "x": 0, "y": 46 },
      "id": 301,
      "options": {
        "reduceOptions": { "calcs": ["lastNotNull"] },
        "orientation": "auto",
        "textMode": "auto",
        "colorMode": "background"
      },
      "targets": [
        {
          "datasource": { "type": "prometheus", "uid": "Prometheus" },
          "expr": "pklpo_dependency_postgres_up",
          "legendFormat": "Postgres",
          "refId": "A"
        },
        {
          "datasource": { "type": "prometheus", "uid": "Prometheus" },
          "expr": "pklpo_dependency_okx_up",
          "legendFormat": "OKX",
          "refId": "B"
        }
      ],
      "title": "USE вЂ” Dependency Health (Postgres / OKX)",
      "type": "stat"
    },

    {
      "datasource": { "type": "prometheus", "uid": "Prometheus" },
      "fieldConfig": {
        "defaults": { "unit": "short", "custom": { "lineWidth": 2 } },
        "overrides": []
      },
      "gridPos": { "h": 5, "w": 9, "x": 6, "y": 46 },
      "id": 302,
      "options": { "tooltip": { "mode": "multi" }, "legend": { "displayMode": "list" } },
      "targets": [
        {
          "datasource": { "type": "prometheus", "uid": "Prometheus" },
          "expr": "pklpo_swap_sync_db_write_latency_avg_ms",
          "legendFormat": "DB write avg ms (mode={{mode}})",
          "refId": "A"
        },
        {
          "datasource": { "type": "prometheus", "uid": "Prometheus" },
          "expr": "pklpo_swap_sync_db_write_latency_p95_ms",
          "legendFormat": "DB write p95 ms legacy (mode={{mode}})",
          "refId": "B"
        }
      ],
      "title": "USE вЂ” DB Write Latency Gauges (avg / p95 legacy)",
      "type": "timeseries"
    },

    {
      "datasource": { "type": "prometheus", "uid": "Prometheus" },
      "fieldConfig": {
        "defaults": { "unit": "short", "custom": { "lineWidth": 2 } },
        "overrides": []
      },
      "gridPos": { "h": 5, "w": 9, "x": 15, "y": 46 },
      "id": 303,
      "options": { "tooltip": { "mode": "multi" }, "legend": { "displayMode": "list" } },
      "targets": [
        {
          "datasource": { "type": "prometheus", "uid": "Prometheus" },
          "expr": "pklpo_swap_sync_api_rate_limit_hits",
          "legendFormat": "API 429s (mode={{mode}})",
          "refId": "A"
        },
        {
          "datasource": { "type": "prometheus", "uid": "Prometheus" },
          "expr": "pklpo_swap_sync_api_timeouts",
          "legendFormat": "API timeouts (mode={{mode}})",
          "refId": "B"
        }
      ],
      "title": "USE вЂ” API Saturation (rate limits / timeouts)",
      "type": "timeseries"
    }

  ],
  "refresh": "30s",
  "schemaVersion": 38,
  "tags": ["pklpo", "observability", "v1"],
  "templating": {
    "list": [
      {
        "current": {},
        "hide": 0,
        "includeAll": false,
        "label": "run_id",
        "multi": false,
        "name": "run_id",
        "options": [],
        "query": "",
        "queryValue": "",
        "skipUrlSync": false,
        "type": "textbox"
      }
    ]
  },
  "time": { "from": "now-1h", "to": "now" },
  "timepicker": {},
  "timezone": "browser",
  "title": "PKLPO Pipeline Observability v1",
  "uid": "pklpo-pipeline-obs-v1",
  "version": 1
}
